dialog_sentry/__init__.py
dialog_sentry/plugin.py
dialog_sentry-0.1.0.dist-info/METADATA
dialog_sentry-0.1.0.dist-info/WHEEL
dialog_sentry-0.1.0.dist-info/entry_points.txt
dialog_sentry-0.1.0.dist-info/RECORD
