Metadata-Version: 2.1
Name: dialog-sentry
Version: 0.1.0
Summary: Sentry plugin for talkdai/dialog
Author: Walison Filipe
Author-email: walisonfilipe@hotmail.com
Requires-Python: >=3.10,<4.0
Classifier: Programming Language :: Python :: 3
Classifier: Programming Language :: Python :: 3.10
Classifier: Programming Language :: Python :: 3.11
Classifier: Programming Language :: Python :: 3.12
Requires-Dist: python-decouple (>=3.8,<4.0)
Requires-Dist: sentry-sdk (>=1.40.2,<2.0.0)
